knp_utils/__init__.py
knp_utils/errors.py
knp_utils/knp_job.py
knp_utils/logger_unit.py
knp_utils/models.py
knp_utils/utils.py
knp_utils/db_handlers/__init__.py
knp_utils/db_handlers/base.py
knp_utils/db_handlers/leveldb_handler.py
knp_utils/db_handlers/sqlite3_handler.py
knp_utils-0.42.dist-info/METADATA
knp_utils-0.42.dist-info/RECORD
knp_utils-0.42.dist-info/WHEEL
knp_utils-0.42.dist-info/top_level.txt
tests/__init__.py
tests/test_knp_job.py
tests/resources/__init__.py
