Metadata-Version: 2.1
Name: knp-utils
Version: 0.42
Summary: Wrapper scripts for Japanese parser `KNP`
Home-page: https://github.com/Kensuke-Mitsuzawa/knp-utils-py
Author: Kensuke Mitsuzawa
Author-email: kensuke.mit@gmail.com
License: MIT
Platform: UNKNOWN
Classifier: Development Status :: 5 - Production/Stable
Classifier: License :: OSI Approved :: MIT License
Classifier: Programming Language :: Python
Classifier: Natural Language :: Japanese
Classifier: Topic :: Scientific/Engineering :: Artificial Intelligence
Classifier: Programming Language :: Python :: 2.7
Classifier: Programming Language :: Python :: 3.5
Requires-Dist: joblib
Requires-Dist: six
Requires-Dist: pexpect
Requires-Dist: more-itertools
Requires-Dist: jaconv
